scp_and_rcp_import_tool/__init__.py
scp_and_rcp_import_tool/main.py
scp_and_rcp_import_tool/utils.py
scp_and_rcp_import_tool-0.1.0.dist-info/LICENSE
scp_and_rcp_import_tool-0.1.0.dist-info/METADATA
scp_and_rcp_import_tool-0.1.0.dist-info/WHEEL
scp_and_rcp_import_tool-0.1.0.dist-info/entry_points.txt
scp_and_rcp_import_tool-0.1.0.dist-info/top_level.txt
scp_and_rcp_import_tool-0.1.0.dist-info/RECORD
